openloss/__init__.py
openloss/src/__init__.py
openloss/src/eos.py
openloss/src/mel.py
openloss/src/osl.py
openloss/tests/__init__.py
openloss/tests/test_loss.py
openloss-0.0.2.dist-info/LICENSE
openloss-0.0.2.dist-info/METADATA
openloss-0.0.2.dist-info/WHEEL
openloss-0.0.2.dist-info/top_level.txt
openloss-0.0.2.dist-info/RECORD
