Metadata-Version: 2.1
Name: openloss
Version: 0.0.2
Summary: Cost functions designed for open-set classification tasks, namely, Entropic Open-set, ObjectoSphere and Maximal-Entropy Loss.
Home-page: https://github.com/rafaelvareto/maximal-entropy-loss
Author: Rafael Vareto
Author-email: rafael@vareto.com.br
Classifier: License :: OSI Approved :: GNU General Public License v3 (GPLv3)
Classifier: Operating System :: OS Independent
Classifier: Programming Language :: Python :: 3
Requires-Python: >=3.8
License-File: LICENSE
Requires-Dist: torch
Requires-Dist: pytest >=7.0
